pyowo/__init__.py
pyowo/owo.py
pyowo-1.0.1.dist-info/LICENSE
pyowo-1.0.1.dist-info/WHEEL
pyowo-1.0.1.dist-info/METADATA
pyowo-1.0.1.dist-info/RECORD
